textual_pdf/__init__.py
textual_pdf/exceptions.py
textual_pdf/pdf_viewer.py
textual_pdf-0.1.7.dist-info/METADATA
textual_pdf-0.1.7.dist-info/WHEEL
textual_pdf-0.1.7.dist-info/entry_points.txt
textual_pdf-0.1.7.dist-info/RECORD
