Metadata-Version: 2.4
Name: textual-pdf
Version: 0.1.7
Summary: Display PDF files in textual widgets!
Project-URL: Issues, https://github.com/NSPC911/textual-pdf/issues
Project-URL: Source, https://github.com/NSPC911/textual-pdf
Author: NSPC911
Keywords: pdf,python,textual,tui
Classifier: Development Status :: 5 - Production/Stable
Classifier: License :: OSI Approved :: MIT License
Classifier: Programming Language :: Python :: 3.13
Classifier: Topic :: Utilities
Requires-Python: >=3.13
Requires-Dist: click>=8.2.1
Requires-Dist: pillow>=11.3.0
Requires-Dist: pymupdf>=1.21.64
Requires-Dist: textual-image>=0.8.3
Requires-Dist: textual>=5.3.0
